Workbook

Sheet Catálogo de Costos
A1: ZENET · Catálogo de Costos Fase 0
A2: Declaración de todos los costos · valores hipótesis de doc 04 viabilidad económica + doc 01 operational readiness · ajustar con valores reales · Tipo de cambio ref ~$20 MXN/USD
A4: Categoría | B4: Concepto | C4: Descripción | D4: Tipo | E4: Frecuencia | F4: Costo MXN | G4: Costo USD | H4: Tier | I4: Status | J4: Notas
A5: Software infra | B5: Vercel | C5: Frontend hosting (Hobby free) | D5: Fijo | E5: Mensual | F5: 0 | G5: 0 | H5: Tier 1 | I5: Activo | J5: Free cubre Phase 0 · Pro $20 USD al cruzar 100GB bandwidth
A6: Software infra | B6: Railway | C6: Backend hosting FastAPI (Hobby) | D6: Fijo | E6: Mensual | F6: 100 | G6: 5 | H6: Tier 1 | I6: Activo | J6: $5 usage credits incluidos · sube con traffic
A7: Software infra | B7: Supabase | C7: DB + Auth + Storage (Free) | D7: Fijo | E7: Mensual | F7: 0 | G7: 0 | H7: Tier 1 | I7: Activo | J7: Free cubre 5 clientes · Pro $25 USD al escalar
A8: Software infra | B8: Langfuse | C8: AI monitoring (Free) | D8: Fijo | E8: Mensual | F8: 0 | G8: 0 | H8: Tier 1 | I8: Activo | J8: Free 50K obs · Hobby $26 USD al escalar
A9: Software infra | B9: Sentry | C9: Error tracking (Free) | D9: Fijo | E9: Mensual | F9: 0 | G9: 0 | H9: Tier 1 | I9: Activo | J9: Free 5K errors · Team $26 USD al escalar
A10: Software infra | B10: PostHog | C10: Product analytics (Free) | D10: Fijo | E10: Mensual | F10: 0 | G10: 0 | H10: Tier 1 | I10: Activo | J10: Free 1M events · Pro $100-300 USD al escalar
A11: Software infra | B11: GitHub | C11: Repo (Free Org) | D11: Fijo | E11: Mensual | F11: 0 | G11: 0 | H11: Tier 1 | I11: Activo | J11: Sin branch protection enforcement
A12: Software infra | B12: Dominio zenet.mx | C12: Registro dominio | D12: Fijo | E12: Anual | F12: 40 | G12: 2 | H12: Tier 1 | I12: Activo | J12: $300-500 MXN/año · amortizado mensual
A13: Founder dev tools | B13: Anthropic Max | C13: Plan personal dev + AI | D13: Fijo | E13: Mensual | F13: 2000 | G13: 100 | H13: Tier 1 | I13: Activo | J13: Dev + personal · NO es cliente API
A14: Founder dev tools | B14: Figma | C14: Pro · diseño/UI | D14: Fijo | E14: Mensual | F14: 400 | G14: 20 | H14: Tier 1 | I14: Pending | J14: Rango $300-600 MXN
A15: Founder dev tools | B15: Notion | C15: Plus · workspace | D15: Fijo | E15: Mensual | F15: 200 | G15: 10 | H15: Tier 1 | I15: Activo | J15: Free Tier
A16: Founder dev tools | B16: Adobe | C16: Creative Cloud · assets | D16: Fijo | E16: Mensual | F16: 1100 | G16: 55 | H16: Tier 1 | I16: Pending
A17: Founder dev tools | B17: Google Workspace | C17: Email empresarial + collab | D17: Fijo | E17: Mensual | F17: 120 | G17: 6 | H17: Tier 1 | I17: Pending | J17: admin@zenetapp.com
A18: Professional services | B18: Lawyer | C18: Engagement 6 meses (MSA+DPA+Adendum SF) | D18: Fijo | E18: Mensual | F18: 3400 | G18: 170 | H18: Tier 2.0 | I18: Pending | J18: 20,400 MXN/6 meses · activa con LOI gate · NO incluye trámites
A19: Professional services | B19: Contador | C19: Despacho contable mensual | D19: Fijo | E19: Mensual | F19: 500 | G19: 25 | H19: Tier 2.0 | I19: Pending | J19: Activa cuando primer cobro confirmado
A20: Professional services | B20: PAC CFDI | C20: Facturama/Konfio timbrado | D20: Fijo | E20: Mensual | F20: 350 | G20: 18 | H20: Tier 2.0 | I20: Pending | J20: $200-500 MXN · activa con primer cobro
A21: Hardware | B21: MacBook Pro M4 | C21: Upgrade desde 2019 Intel i7 | D21: One-time | E21: One-time (amort 12m) | F21: 6000 | G21: 300 | H21: Tier 1 | I21: Pending | J21: $60-80K MXN amortizado 12 meses · decisión founder
A22: Setup one-time | B22: PFAE setup SAT | C22: RFC actividad empresarial | D22: One-time | E22: One-time | F22: 1000 | G22: 50 | H22: Tier 1 | I22: Pending | J22: $0-2K MXN · 1 día · cita SAT
A23: Setup one-time | B23: Cuenta bancaria | C23: Banco empresarial | D23: One-time | E23: One-time | F23: 0 | G23: 0 | H23: Tier 1 | I23: Pending | J23: Gratis · ~1 semana
A24: Setup one-time | B24: IMPI marca | C24: Trademark registro 'Zenet' | D24: One-time | E24: One-time | F24: 4000 | G24: 200 | H24: Tier 1 | I24: Pending | J24: $3-5K MXN · 4-6 meses approval · protege desde filing
A25: Setup one-time | B25: Website básico | C25: Landing + Aviso Privacidad draft | D25: One-time | E25: One-time | F25: 1500 | G25: 75 | H25: Tier 1 | I25: Pending | J25: $0-3K MXN DIY (Webflow/Framer)
A26: Vendor variable | B26: Anthropic API | C26: LLM inference per cliente Esencial | D26: Variable | E26: Mensual/cliente | F26: 700 | G26: 35 | H26: Tier 2.0 | I26: Pending | J26: $20-50 USD/cliente sin Capa 1 · -50% con prompt caching
A27: Vendor variable | B27: WhatsApp Business API | C27: Messaging per cliente | D27: Variable | E27: Mensual/cliente | F27: 200 | G27: 10 | H27: Tier 1.5 | I27: Pending | J27: $5-15 USD/cliente · provider Meta direct TBD
A28: Vendor variable | B28: Supabase compute | C28: DB compute scaling per cliente | D28: Variable | E28: Mensual/cliente | F28: 0 | G28: 0 | H28: Tier 1 | I28: Activo | J28: Free tier Phase 0 · $1-5 USD al escalar
... A30: Vendor variable | B30: Stripe/Conekta fee | C30: Payment processing ~3% revenue | D30: Variable | E30: Per transacción | F30: 90 | G30: 4 | H30: Tier 2.0 | I30: Pending | J30: 2.9-3.6% del cobro

Sheet Tracking Mensual
A1: ZENET · Tracking Mensual de Costos Fase 0 (MXN)
A2: Llenar con valores REALES cada mes · fijos activos pre-poblados (baseline) · variables/one-time se llenan cuando ocurren · totales automáticos
A3: Concepto | B3: Jun 2026 | C3: Jul 2026 | D3: Ago 2026 | E3: Sep 2026 | F3: Oct 2026 | G3: Nov 2026 | H3: Dic 2026 | I3: Ene 2027 | J3: Feb 2027 | K3: Mar 2027 | L3: Abr 2027 | M3: May 2027 | N3: TOTAL
A4: COSTOS FIJOS
A5: Vercel | B5: 0 | C5: 0 | D5: 0 | E5: 0 | F5: 0 | G5: 0 | H5: 0 | I5: 0 | J5: 0 | K5: 0 | L5: 0 | M5: 0 | N5: =SUM(B5:M5) -> 0
A6: Railway | B6: 100 | C6: 100 | D6: 100 | E6: 100 | F6: 100 | G6: 100 | H6: 100 | I6: 100 | J6: 100 | K6: 100 | L6: 100 | M6: 100 | N6: =SUM(B6:M6) -> 1200
A7: Supabase | B7: 0 | C7: 0 | D7: 0 | E7: 0 | F7: 0 | G7: 0 | H7: 0 | I7: 0 | J7: 0 | K7: 0 | L7: 0 | M7: 0 | N7: =SUM(B7:M7) -> 0
A8: Langfuse | B8: 0 | C8: 0 | D8: 0 | E8: 0 | F8: 0 | G8: 0 | H8: 0 | I8: 0 | J8: 0 | K8: 0 | L8: 0 | M8: 0 | N8: =SUM(B8:M8) -> 0
A9: Sentry | B9: 0 | C9: 0 | D9: 0 | E9: 0 | F9: 0 | G9: 0 | H9: 0 | I9: 0 | J9: 0 | K9: 0 | L9: 0 | M9: 0 | N9: =SUM(B9:M9) -> 0
A10: PostHog | B10: 0 | C10: 0 | D10: 0 | E10: 0 | F10: 0 | G10: 0 | H10: 0 | I10: 0 | J10: 0 | K10: 0 | L10: 0 | M10: 0 | N10: =SUM(B10:M10) -> 0
A11: GitHub | B11: 0 | C11: 0 | D11: 0 | E11: 0 | F11: 0 | G11: 0 | H11: 0 | I11: 0 | J11: 0 | K11: 0 | L11: 0 | M11: 0 | N11: =SUM(B11:M11) -> 0
A12: Dominio (amort.) | B12: 0 | C12: 0 | D12: 0 | E12: 0 | F12: 0 | G12: 0 | H12: 0 | I12: 0 | J12: 0 | K12: 0 | L12: 0 | M12: 0 | N12: =SUM(B12:M12) -> 0
A13: Anthropic Max | B13: 2000 | C13: 2000 | D13: 2000 | E13: 2000 | F13: 2000 | G13: 2000 | H13: 2000 | I13: 2000 | J13: 2000 | K13: 2000 | L13: 2000 | M13: 2000 | N13: =SUM(B13:M13) -> 24000
A14: Figma | B14: 0 | C14: 0 | D14: 0 | E14: 0 | F14: 0 | G14: 0 | H14: 0 | I14: 0 | J14: 0 | K14: 0 | L14: 0 | M14: 0 | N14: =SUM(B14:M14) -> 0
A15: Notion | B15: 0 | C15: 0 | D15: 0 | E15: 0 | F15: 0 | G15: 0 | H15: 0 | I15: 0 | J15: 0 | K15: 0 | L15: 0 | M15: 0 | N15: =SUM(B15:M15) -> 0
A16: Adobe | B16: 0 | C16: 0 | D16: 0 | E16: 0 | F16: 0 | G16: 0 | H16: 0 | I16: 0 | J16: 0 | K16: 0 | L16: 0 | M16: 0 | N16: =SUM(B16:M16) -> 0
... A20: PAC CFDI | B20: 0 | C20: 0 | D20: 0 | E20: 0 | F20: 0 | G20: 0 | H20: 0 | I20: 0 | J20: 0 | K20: 0 | L20: 0 | M20: 0 | N20: =SUM(B20:M20) -> 0
A21: Subtotal Fijos | B21: =SUM(B5:B20) -> 2100 | C21: =SUM(C5:C20) -> 2100 | D21: =SUM(D5:D20) -> 2100 | E21: =SUM(E5:E20) -> 2100 | F21: =SUM(F5:F20) -> 2100 | G21: =SUM(G5:G20) -> 2100 | H21: =SUM(H5:H20) -> 2100 | I21: =SUM(I5:I20) -> 2100 | ... M21: =SUM(M5:M20) -> 2100 | N21: =SUM(B21:M21) -> 25200
A22: COSTOS VARIABLES (por cliente)
A23: Anthropic API (clientes) | B23: 0 | C23: 0 | D23: 0 | E23: 0 | F23: 0 | G23: 0 | H23: 0 | I23: 0 | J23: 0 | K23: 0 | L23: 0 | M23: 0 | N23: =SUM(B23:M23) -> 0
A24: WhatsApp Business (clientes) | B24: 0 | C24: 0 | D24: 0 | E24: 0 | F24: 0 | G24: 0 | H24: 0 | I24: 0 | J24: 0 | K24: 0 | L24: 0 | M24: 0 | N24: =SUM(B24:M24) -> 0
A25: Supabase compute (clientes) | B25: 0 | C25: 0 | D25: 0 | E25: 0 | F25: 0 | G25: 0 | H25: 0 | I25: 0 | J25: 0 | K25: 0 | L25: 0 | M25: 0 | N25: =SUM(B25:M25) -> 0
A26: PAC timbre (clientes) | B26: 0 | C26: 0 | D26: 0 | E26: 0 | F26: 0 | G26: 0 | H26: 0 | I26: 0 | J26: 0 | K26: 0 | L26: 0 | M26: 0 | N26: =SUM(B26:M26) -> 0
A27: Stripe/Conekta fee | B27: 0 | C27: 0 | D27: 0 | E27: 0 | F27: 0 | G27: 0 | H27: 0 | I27: 0 | J27: 0 | K27: 0 | L27: 0 | M27: 0 | N27: =SUM(B27:M27) -> 0
A28: Subtotal Variables | B28: =SUM(B23:B27) -> 0 | C28: =SUM(C23:C27) -> 0 | D28: =SUM(D23:D27) -> 0 | E28: =SUM(E23:E27) -> 0 | F28: =SUM(F23:F27) -> 0 | G28: =SUM(G23:G27) -> 0 | H28: =SUM(H23:H27) -> 0 | I28: =SUM(I23:I27) -> 0 | ... M28: =SUM(M23:M27) -> 0 | N28: =SUM(B28:M28) -> 0
A29: COSTOS ONE-TIME
A30: MacBook Pro M5 (amort.) | B30: 0 | C30: 0 | D30: 0 | E30: 0 | F30: 0 | G30: 0 | H30: 0 | I30: 0 | J30: 0 | K30: 0 | L30: 0 | M30: 0 | N30: =SUM(B30:M30) -> 0
A31: PFAE setup SAT | B31: 0 | C31: 0 | D31: 0 | E31: 0 | F31: 0 | G31: 0 | H31: 0 | I31: 0 | J31: 0 | K31: 0 | L31: 0 | M31: 0 | N31: =SUM(B31:M31) -> 0
A32: Cuenta bancaria | B32: 0 | C32: 0 | D32: 0 | E32: 0 | F32: 0 | G32: 0 | H32: 0 | I32: 0 | J32: 0 | K32: 0 | L32: 0 | M32: 0 | N32: =SUM(B32:M32) -> 0
A33: IMPI marca | B33: 0 | C33: 0 | D33: 0 | E33: 0 | F33: 0 | G33: 0 | H33: 0 | I33: 0 | J33: 0 | K33: 0 | L33: 0 | M33: 0 | N33: =SUM(B33:M33) -> 0
A34: Website básico | B34: 0 | C34: 0 | D34: 0 | E34: 0 | F34: 0 | G34: 0 | H34: 0 | I34: 0 | J34: 0 | K34: 0 | L34: 0 | M34: 0 | N34: =SUM(B34:M34) -> 0
A35: Subtotal One-time | B35: =SUM(B30:B34) -> 0 | C35: =SUM(C30:C34) -> 0 | D35: =SUM(D30:D34) -> 0 | E35: =SUM(E30:E34) -> 0 | F35: =SUM(F30:F34) -> 0 | G35: =SUM(G30:G34) -> 0 | H35: =SUM(H30:H34) -> 0 | I35: =SUM(I30:I34) -> 0 | ... M35: =SUM(M30:M34) -> 0 | N35: =SUM(B35:M35) -> 0
A36: TOTAL COSTOS / MES | B36: =B21+B28+B35 -> 2100 | C36: =C21+C28+C35 -> 2100 | D36: =D21+D28+D35 -> 2100 | E36: =E21+E28+E35 -> 2100 | F36: =F21+F28+F35 -> 2100 | G36: =G21+G28+G35 -> 2100 | H36: =H21+H28+H35 -> 2100 | I36: =I21+I28+I35 -> 2100 | ... M36: =M21+M28+M35 -> 2100 | N36: =SUM(B36:M36) -> 25200
A37: Revenue / mes (llenar) | B37: 0 | C37: 0 | D37: 0 | E37: 0 | F37: 0 | G37: 0 | H37: 0 | I37: 0 | J37: 0 | K37: 0 | L37: 0 | M37: 0 | N37: =SUM(B37:M37) -> 0
A38: NET BURN / MES (Revenue - Costos) | B38: =B37-B36 -> -2100 | C38: =C37-C36 -> -2100 | D38: =D37-D36 -> -2100 | E38: =E37-E36 -> -2100 | F38: =F37-F36 -> -2100 | G38: =G37-G36 -> -2100 | H38: =H37-H36 -> -2100 | I38: =I37-I36 -> -2100 | ... M38: =M37-M36 -> -2100 | N38: =SUM(B38:M38) -> -25200

Sheet Dashboard
A1: ZENET · Dashboard Resumen Costos Fase 0
A2: Resumen automático desde Tracking Mensual · ajustar selección de mes según necesidad
A4: Métrica | B4: Valor
A5: Costos Fijos (12m) | B5: ='Tracking Mensual'!N21 -> 25200
A6: Costos Variables (12m) | B6: ='Tracking Mensual'!N28 -> 0
A7: Costos One-time (12m) | B7: ='Tracking Mensual'!N35 -> 0
A8: TOTAL Costos (12m) | B8: ='Tracking Mensual'!N36 -> 25200
A9: Revenue (12m) | B9: ='Tracking Mensual'!N37 -> 0
A10: NET BURN acumulado (12m) | B10: ='Tracking Mensual'!N38 -> -25200
A12: Baseline fijo mensual (Jun 2026) | B12: ='Tracking Mensual'!B21 -> 2100
A14: Notas Dashboard
A15: · Fijos baseline Phase 0 ~$3,960 MXN/mes (founder tools + Railway + dominio · resto free tier).
A16: · Lawyer/Contador/PAC activan en Tier 2.0 (LOI gate · primer cobro confirmado).
A17: · Variables crecen con # clientes · Anthropic dominante (-50% con prompt caching Capa 1).
A18: · One-time (MacBook · IMPI · PFAE · website) se registran en el mes que ocurren.
A19: · Founder time opportunity cost NO incluido (no es cash · ~$40-80K MXN/mes equivalente).
A20: · Trigger upgrade a financial model formal: 3+ design partners Mes 3+ (cf. 02-financial-model scaffold).
